choosealicense/__init__.py
choosealicense/cli.py
choosealicense/ui.py
choosealicense/utils.py
choosealicense/test/conftest.py
choosealicense/test/test_context.py
choosealicense/test/test_generate.py
choosealicense/test/test_info.py
choosealicense/test/test_reach_limit.py
choosealicense/test/test_show.py
choosealicense/test/responses/get_json.py
choosealicense/test/responses/licenses.json
choosealicense/test/responses/not_found.json
choosealicense/test/responses/reach_limit.json
choosealicense/test/responses/licenses/agpl-3.0.json
choosealicense/test/responses/licenses/apache-2.0.json
choosealicense/test/responses/licenses/artistic-2.0.json
choosealicense/test/responses/licenses/bsd-2-clause.json
choosealicense/test/responses/licenses/bsd-3-clause.json
choosealicense/test/responses/licenses/cc0-1.0.json
choosealicense/test/responses/licenses/epl-1.0.json
choosealicense/test/responses/licenses/epl-2.0.json
choosealicense/test/responses/licenses/gpl-2.0.json
choosealicense/test/responses/licenses/gpl-3.0.json
choosealicense/test/responses/licenses/isc.json
choosealicense/test/responses/licenses/lgpl-2.1.json
choosealicense/test/responses/licenses/lgpl-3.0.json
choosealicense/test/responses/licenses/mit.json
choosealicense/test/responses/licenses/mpl-2.0.json
choosealicense/test/responses/licenses/unlicense.json
choosealicense_cli-1.1.0.dist-info/LICENSE
choosealicense_cli-1.1.0.dist-info/METADATA
choosealicense_cli-1.1.0.dist-info/WHEEL
choosealicense_cli-1.1.0.dist-info/entry_points.txt
choosealicense_cli-1.1.0.dist-info/top_level.txt
choosealicense_cli-1.1.0.dist-info/RECORD
