Metadata-Version: 2.1
Name: choosealicense-cli
Version: 1.1.0
Summary: Bring http://choosealicense.com to your terminal
Home-page: http://github.com/lord63/choosealicense-cli
Author: lord63
Author-email: lord63.j@gmail.com
License: MIT
Keywords: license generate cli choosealicense
Platform: UNKNOWN
Classifier: Development Status :: 4 - Beta
Classifier: Intended Audience :: Developers
Classifier: Operating System :: POSIX
Classifier: Operating System :: POSIX :: Linux
Classifier: License :: OSI Approved :: MIT License
Classifier: Programming Language :: Python :: 2
Classifier: Programming Language :: Python :: 2.7
Classifier: Programming Language :: Python :: 3
Classifier: Programming Language :: Python :: 3.4
Classifier: Programming Language :: Python :: 3.5
Classifier: Programming Language :: Python :: 3.6
Requires-Dist: click (>=4.0)
Requires-Dist: requests (>=2.6.0)
